[
  {
    "site": "Hatena",
    "title": "【Hothotレビュー】 M3/M4ユーザーが嫉妬する？M5版MacBook Proの“爆速SSD”がもたらす圧倒的時短効果",
    "link": "https://pc.watch.impress.co.jp/docs/column/hothot/2074593.html",
    "pubDate": "2025-12-25T23:18:52.000Z"
  },
  {
    "site": "Hatena",
    "title": "【大河原克行の「パソコン業界、東奔西走」】 2026年、PCを値上げする？しない？13社にアンケートを取ってみた",
    "link": "https://pc.watch.impress.co.jp/docs/column/gyokai/2074446.html",
    "pubDate": "2025-12-25T21:24:49.000Z"
  },
  {
    "site": "Hatena",
    "title": "PuTTY(パティ)を悪用したサイバー攻撃が増加-正規ツールを使った横移動・情報持ち出しに警戒|セキュリティニュースのセキュリティ対策Lab",
    "link": "https://rocket-boys.co.jp/security-measures-lab/putty-abuse-attacks-rise-using-legit-tool-for-lateral-movement/",
    "pubDate": "2025-12-25T15:44:13.000Z"
  },
  {
    "site": "Hatena",
    "title": "AIと考える Part.2 – 「壁打ち」としてのAI活用",
    "link": "https://blog.szk.cc/2025/12/25/thinking-with-ai-part2/",
    "pubDate": "2025-12-25T15:01:18.000Z"
  },
  {
    "site": "Hatena",
    "title": "斧を研ぎたいのに木が無限に湧く森で｜チャンタマ",
    "link": "https://note.com/tmchannel_/n/n80bc0fbd8edc",
    "pubDate": "2025-12-25T14:58:30.000Z"
  },
  {
    "site": "Hatena",
    "title": "キーボードに添えるだけ。ホームポジションの常識を変えるトラックボール｢Nape Pro｣ ｜ CoSTORY",
    "link": "https://costory.jp/cf-published-sku-groups/1254312814?twclid=23u3uzu0nhaip8kuh91pcql8pm&utm_source=x&utm_medium=cpc&utm_campaign=napepro",
    "pubDate": "2025-12-25T13:04:52.000Z"
  },
  {
    "site": "Hatena",
    "title": "H3ロケット8号機のオンボード画像が公開、「みちびき」の姿に異変",
    "link": "https://news.mynavi.jp/techplus/article/20251225-3871943/",
    "pubDate": "2025-12-25T12:56:04.000Z"
  },
  {
    "site": "Qiita",
    "title": "新人AI禁止令と、その結果の答え合わせ - Qiita",
    "link": "https://qiita.com/WdknWdkn/items/9b7dea889fec59194df5",
    "pubDate": "2025-12-25T06:57:13.000Z"
  },
  {
    "site": "Qiita",
    "title": "新人AI禁止令と、その結果の答え合わせ",
    "link": "https://qiita.com/WdknWdkn/items/9b7dea889fec59194df5?utm_campaign=popular_items&utm_medium=feed&utm_source=popular_items",
    "pubDate": "2025-12-25T05:32:15.000Z"
  },
  {
    "site": "Hatena",
    "title": "2025年「はてなブックマーク年間ランキング」トップ100 - はてなニュース",
    "link": "https://hatenanews.com/articles/hatenabookmark2025",
    "pubDate": "2025-12-25T03:16:53.000Z"
  },
  {
    "site": "Qiita",
    "title": "【TOEIC600→875】仕事終わり1日1時間×3ヶ月で270点伸ばした“本当に効いたAI活用勉強法”",
    "link": "https://qiita.com/shotaloss/items/3542e1d186e888c0482f?utm_campaign=popular_items&utm_medium=feed&utm_source=popular_items",
    "pubDate": "2025-12-25T03:07:01.000Z"
  },
  {
    "site": "Zenn",
    "title": "RAGが苦手な「膨大な会話データ」を検索可能に",
    "link": "https://zenn.dev/knowledgesense/articles/c2baff28b7b2fa",
    "pubDate": "Thu, 25 Dec 2025 01:26:09 GMT"
  },
  {
    "site": "Hatena",
    "title": "SF小説『三体』の元ネタ、300年来の“あの難問”に新展開。カオスの仕組みを数学者が解明と発表【研究紹介】 レバテックラボ（レバテックLAB）",
    "link": "https://levtech.jp/media/article/column/detail_778/",
    "pubDate": "2025-12-25T00:03:09.000Z"
  },
  {
    "site": "Zenn",
    "title": "CTOとして、継承の重要性と退く覚悟の話",
    "link": "https://zenn.dev/aeonpeople/articles/f65886fc86a8a0",
    "pubDate": "Thu, 25 Dec 2025 00:00:02 GMT"
  },
  {
    "site": "Qiita",
    "title": "VS Code全盛期にあえてScreen/Tmuxを伝えたい",
    "link": "https://qiita.com/daikt/items/3202d00e1d8d0944b091?utm_campaign=popular_items&utm_medium=feed&utm_source=popular_items",
    "pubDate": "2025-12-24T22:06:38.000Z"
  },
  {
    "site": "Qiita",
    "title": "ZOZO開発組織の2025年の振り返りと現状",
    "link": "https://qiita.com/sonots/items/785aa480635a8a5443f6?utm_campaign=popular_items&utm_medium=feed&utm_source=popular_items",
    "pubDate": "2025-12-24T22:02:46.000Z"
  },
  {
    "site": "Zenn",
    "title": "うっかりミスでアクティブユーザー1万人超えのサービスをサ終させた話",
    "link": "https://zenn.dev/mnonamer/articles/yarakashi-2025-eos-with-10k-au",
    "pubDate": "Wed, 24 Dec 2025 15:00:01 GMT"
  },
  {
    "site": "Zenn",
    "title": "Go 1.26 は、軽くなり速くなる",
    "link": "https://zenn.dev/mattn/articles/64c47f937a522f",
    "pubDate": "Wed, 24 Dec 2025 15:00:01 GMT"
  },
  {
    "site": "Zenn",
    "title": "ゲームエンジンを自作する際のテキスト描画機能",
    "link": "https://zenn.dev/reputeless/articles/siv3d-text-rendering-v8",
    "pubDate": "Wed, 24 Dec 2025 14:05:27 GMT"
  },
  {
    "site": "Zenn",
    "title": "5年間 Laravel を使って辿り着いた，AI 時代に考える「なんちゃってクリーンアーキテクチャ」のその先",
    "link": "https://zenn.dev/yumemi_inc/articles/ebc6e634fa57a1",
    "pubDate": "Wed, 24 Dec 2025 13:00:45 GMT"
  },
  {
    "site": "Zenn",
    "title": "Luna UI - JS/Moonbit のための宣言的UI. 軽量、高速、そして WebComponents First",
    "link": "https://zenn.dev/mizchi/articles/moonbit-luna-ui",
    "pubDate": "Wed, 24 Dec 2025 09:43:47 GMT"
  },
  {
    "site": "Zenn",
    "title": "新しいデザインシステム・コンポーネント管理のかたち「shadcn/ui registry」",
    "link": "https://zenn.dev/imaimai17468/articles/774e42f5613b15",
    "pubDate": "Wed, 24 Dec 2025 09:02:17 GMT"
  },
  {
    "site": "Qiita",
    "title": "昔触った「Tekton」を思い出しながら、初心者向けに CI/CD の基本概念を整理してみる",
    "link": "https://qiita.com/ta1ch1-sa1to/items/958cf3943266d7deca21?utm_campaign=popular_items&utm_medium=feed&utm_source=popular_items",
    "pubDate": "2025-12-24T03:57:51.000Z"
  },
  {
    "site": "Zenn",
    "title": "新卒3年目が、AIフル活用で設計力が爆あがりした話",
    "link": "https://zenn.dev/ourly_tech_blog/articles/9301cc0acdd09c",
    "pubDate": "Wed, 24 Dec 2025 03:00:05 GMT"
  },
  {
    "site": "Zenn",
    "title": "5年ぶりにAngularを触ったら、審美眼もアップデートされた話",
    "link": "https://zenn.dev/okunokentaro/articles/01kd4hz2mf113xt8vwkt012e73",
    "pubDate": "Wed, 24 Dec 2025 01:51:29 GMT"
  },
  {
    "site": "Qiita",
    "title": "Flutterにおける非同期処理のレースコンディションとその対策",
    "link": "https://qiita.com/natsuko_nagaoka/items/b0de963db4d181c3bd67?utm_campaign=popular_items&utm_medium=feed&utm_source=popular_items",
    "pubDate": "2025-12-23T22:05:38.000Z"
  },
  {
    "site": "Qiita",
    "title": "【脱・天気の話】人事が教える、面接・1on1で「沈黙が怖くなくなる」アイスブレイク術",
    "link": "https://qiita.com/ryoTSS/items/c8f4508d55f50326753e?utm_campaign=popular_items&utm_medium=feed&utm_source=popular_items",
    "pubDate": "2025-12-23T22:05:29.000Z"
  },
  {
    "site": "Qiita",
    "title": "NotebookLMで60ページ超の登壇スライド作成してみた",
    "link": "https://qiita.com/simdroid/items/236886451b6aef7162b5?utm_campaign=popular_items&utm_medium=feed&utm_source=popular_items",
    "pubDate": "2025-12-23T13:01:41.000Z"
  },
  {
    "site": "Qiita",
    "title": "SD LoRA学習: OneTrainer導入 (JP-EN)",
    "link": "https://qiita.com/cody_kotichas/items/95c27feb0256e6028c27?utm_campaign=popular_items&utm_medium=feed&utm_source=popular_items",
    "pubDate": "2025-12-23T05:21:44.000Z"
  },
  {
    "site": "Qiita",
    "title": "Google Cloud認定資格を全て取得したので学習方法等をまとめる",
    "link": "https://qiita.com/takahiro_fukushima/items/9c143c46dcac20a6bf62?utm_campaign=popular_items&utm_medium=feed&utm_source=popular_items",
    "pubDate": "2025-12-22T22:07:21.000Z"
  }
]